.gitignore
CHANGES.txt
MANIFEST.in
README.md
README.txt
TODO.txt
setup.cfg
setup.py
pcommerce/__init__.py
pcommerce.payment.paypal.egg-info/PKG-INFO
pcommerce.payment.paypal.egg-info/SOURCES.txt
pcommerce.payment.paypal.egg-info/dependency_links.txt
pcommerce.payment.paypal.egg-info/entry_points.txt
pcommerce.payment.paypal.egg-info/namespace_packages.txt
pcommerce.payment.paypal.egg-info/not-zip-safe
pcommerce.payment.paypal.egg-info/requires.txt
pcommerce.payment.paypal.egg-info/top_level.txt
pcommerce/payment/__init__.py
pcommerce/payment/paypal/__init__.py
pcommerce/payment/paypal/config.py
pcommerce/payment/paypal/configure.zcml
pcommerce/payment/paypal/data.py
pcommerce/payment/paypal/interfaces.py
pcommerce/payment/paypal/plugin.py
pcommerce/payment/paypal/setuphandlers.py
pcommerce/payment/paypal/browser/__init__.py
pcommerce/payment/paypal/browser/configlet.pt
pcommerce/payment/paypal/browser/configlet.py
pcommerce/payment/paypal/browser/configure.zcml
pcommerce/payment/paypal/browser/confirmation.pt
pcommerce/payment/paypal/browser/confirmation.py
pcommerce/payment/paypal/browser/icon.gif
pcommerce/payment/paypal/browser/logo.gif
pcommerce/payment/paypal/browser/overview.pt
pcommerce/payment/paypal/browser/overview.py
pcommerce/payment/paypal/browser/payment.py
pcommerce/payment/paypal/browser/process.py
pcommerce/payment/paypal/i18n/pcommerce-de.po
pcommerce/payment/paypal/i18n/pcommerce-nl.po
pcommerce/payment/paypal/i18n/pcommerce.pot
pcommerce/payment/paypal/profiles/default/controlpanel.xml
pcommerce/payment/paypal/profiles/default/metadata.xml
pcommerce/payment/paypal/profiles/default/pcommerce.payment.paypal_various.txt