Metadata-Version: 1.1
Name: pcommerce.payment.paypal
Version: 0.4
Summary: A paypal payment method for PCommerce
Home-page: https://github.com/Gomez/pcommerce.payment.paypal
Author: Steffen Lindner
Author-email: gomez@flexiabel.de
License: GPL
Platform: UNKNOWN
Classifier: Programming Language :: Python
Classifier: Topic :: Software Development :: Libraries :: Python Modules
